sep/__init__.py
sep/evaluate.py
sep/examine.py
sep/extract.py
sep/process.py
sep/splits.py
sep/_commons/__init__.py
sep/_commons/gui.py
sep/_commons/imgutil.py
sep/_commons/movies.py
sep/_commons/utils.py
sep/_commons/visuals.py
sep/assessors/__init__.py
sep/assessors/detailer.py
sep/assessors/metricer.py
sep/assessors/metrics.py
sep/assessors/plott.py
sep/assessors/regions.py
sep/inspect/__init__.py
sep/inspect/metrics.py
sep/inspect/regions.py
sep/inspect/start.py
sep/inspect/utils.py
sep/loaders/__init__.py
sep/loaders/files.py
sep/loaders/images.py
sep/loaders/loader.py
sep/loaders/movies.py
sep/loaders/youtube.py
sep/producers/__init__.py
sep/producers/images.py
sep/producers/producer.py
sep/producers/realtime.py
sep/producers/segmentnn.py
sep/savers/__init__.py
sep/savers/images.py
sep/savers/movies.py
sep/savers/saver.py
tests/test__commons/__init__.py
tests/test__commons/test_imgutil.py
tests/test__commons/test_movies.py
tests/test__commons/test_utils.py
tests/test_assessors/__init__.py
tests/test_assessors/test_metricer.py
tests/test_assessors/test_regions.py
tests/test_inspect/__init__.py
tests/test_inspect/test_regions.py
tests/test_loaders/__init__.py
tests/test_loaders/test_images.py
tests/test_loaders/test_movies.py
tests/test_loaders/test_youtube.py
tests/test_producers/__init__.py
tests/test_producers/test_producer.py
tests/test_savers/__init__.py
tests/test_savers/test_images.py
tests/test_savers/test_movies.py
semevalplatform-0.0.11.post1.dist-info/LICENSE
semevalplatform-0.0.11.post1.dist-info/METADATA
semevalplatform-0.0.11.post1.dist-info/WHEEL
semevalplatform-0.0.11.post1.dist-info/top_level.txt
semevalplatform-0.0.11.post1.dist-info/RECORD
