Metadata-Version: 2.1
Name: semevalplatform
Version: 0.0.11.post1
Summary: Semantic Evaluation Platform
Home-page: https://github.com/Fafa87/SEP
Author: Filip Mroz
Author-email: fafafft@gmail.com
License: BSD
Keywords: evaluation,semantic,segmentation,benchmark
Classifier: Development Status :: 2 - Pre-Alpha
Classifier: Intended Audience :: Science/Research
Classifier: License :: OSI Approved :: BSD License
Classifier: Operating System :: OS Independent
Classifier: Programming Language :: Python :: 3.6
Classifier: Programming Language :: Python :: 3.7
Classifier: Topic :: Scientific/Engineering
License-File: LICENSE
Requires-Dist: numpy
Requires-Dist: fire
Requires-Dist: imageio
Requires-Dist: pathlib
Requires-Dist: attrdict
Requires-Dist: tqdm
Requires-Dist: pandas
Requires-Dist: matplotlib
Requires-Dist: notebook
Requires-Dist: jupyter-contrib-nbextensions
Requires-Dist: scikit-image
Requires-Dist: opencv-python
Requires-Dist: pafy
Requires-Dist: youtube-dl
